expression_copilot/__init__.py
expression_copilot/_torch_regression.py
expression_copilot/baseline.py
expression_copilot/mi.py
expression_copilot/model.py
expression_copilot/pp.py
expression_copilot/utils.py
expression_copilot-0.3.0.dist-info/METADATA
expression_copilot-0.3.0.dist-info/WHEEL
expression_copilot-0.3.0.dist-info/licenses/LICENSE
expression_copilot-0.3.0.dist-info/RECORD
