Metadata-Version: 2.4
Name: expression_copilot
Version: 0.3.0
Summary: Quantifying predictability of gene expression from histology image
License: MIT
License-File: LICENSE
Keywords: spatialomics,bioinfomatics,mutualinformation
Author: Chen-Rui Xia
Author-email: xiachenrui@mail.cbi.pku.edu.cn
Requires-Python: >=3.10
Classifier: Intended Audience :: Science/Research
Classifier: License :: OSI Approved :: MIT License
Classifier: Natural Language :: English
Classifier: Operating System :: MacOS :: MacOS X
Classifier: Operating System :: POSIX :: Linux
Classifier: Programming Language :: Python :: 3
Classifier: Programming Language :: Python :: 3.10
Classifier: Programming Language :: Python :: 3.11
Classifier: Programming Language :: Python :: 3.12
Classifier: Programming Language :: Python :: 3.13
Classifier: Programming Language :: Python :: 3.14
Classifier: Topic :: Scientific/Engineering :: Bio-Informatics
Provides-Extra: dev
Provides-Extra: torch
Requires-Dist: annoy
Requires-Dist: black ; extra == "dev"
Requires-Dist: einops ; extra == "dev"
Requires-Dist: faiss-cpu
Requires-Dist: ipython
Requires-Dist: isort ; extra == "dev"
Requires-Dist: jupyter_contrib_nbextensions ; extra == "dev"
Requires-Dist: jupyterlab ; extra == "dev"
Requires-Dist: jupytext ; extra == "dev"
Requires-Dist: leidenalg
Requires-Dist: lightgbm
Requires-Dist: loguru
Requires-Dist: nbformat ; extra == "dev"
Requires-Dist: numpy (>1.21)
Requires-Dist: opencv-python ; extra == "dev"
Requires-Dist: openslide-bin ; extra == "dev"
Requires-Dist: openslide-python ; extra == "dev"
Requires-Dist: patchworklib ; extra == "dev"
Requires-Dist: pre-commit ; extra == "dev"
Requires-Dist: py-spy ; extra == "dev"
Requires-Dist: pynndescent (>=0.5)
Requires-Dist: pytest ; extra == "dev"
Requires-Dist: pytest-cov ; extra == "dev"
Requires-Dist: pytest-sugar ; extra == "dev"
Requires-Dist: pytest-xdist ; extra == "dev"
Requires-Dist: pytorch-lightning (>=2.1) ; extra == "torch"
Requires-Dist: pyyaml
Requires-Dist: ray[default] ; extra == "dev"
Requires-Dist: scanpy (>=1.9)
Requires-Dist: scikit-image ; extra == "dev"
Requires-Dist: scikit-misc (>=0.3)
Requires-Dist: scipy (>1.14)
Requires-Dist: tbb ; extra == "dev"
Requires-Dist: torch (>=2.0) ; extra == "torch"
Requires-Dist: torchaudio ; extra == "torch"
Requires-Dist: torchvision ; extra == "torch"
Project-URL: Documentation, https://github.com/gao-lab/ExpressionCopilot
Project-URL: Homepage, https://github.com/gao-lab/ExpressionCopilot
Project-URL: Repository, https://github.com/gao-lab/ExpressionCopilot
